{
  "required_global_full_triggers": [
    ".github/",
    "justfile",
    "rules_engine/Cargo.lock",
    "rules_engine/Cargo.toml",
    "scripts/review/review_scope.py",
    "scripts/review/review_scope_config.json"
  ],
  "global_full_triggers": [
    ".github/",
    "justfile",
    "rules_engine/Cargo.lock",
    "rules_engine/Cargo.toml",
    "scripts/review/review_perf_log.py",
    "scripts/review/review_runner.py",
    "scripts/review/review_scope.py",
    "scripts/review/review_scope_config.json",
    "rules_engine/tabula/"
  ],
  "parser": {
    "crate_seeds": [
      "parser",
      "parser_benchmarks",
      "parser_tests"
    ],
    "path_prefixes": [
      "rules_engine/benchmarks/parser_benchmarks/",
      "rules_engine/src/parser/",
      "rules_engine/tests/parser_tests/"
    ]
  },
  "tv": {
    "crate_seeds": [
      "tv",
      "tv_tests"
    ],
    "path_prefixes": [
      "rules_engine/src/tv/",
      "rules_engine/tests/tv_tests/"
    ]
  },
  "csharp": {
    "crate_seeds": [],
    "path_prefixes": [
      "client/Assets/"
    ]
  },
  "always_run_steps": [
    "check-snapshots",
    "check-format",
    "check-docs-format",
    "check-token-limits",
    "review-scope-validate",
    "build",
    "clippy",
    "style-validator",
    "rlf-lint",
    "test-core"
  ],
  "markdown_only_skip_steps": [
    "build",
    "clippy",
    "rlf-lint",
    "test-core",
    "python-test",
    "pyre-check",
    "parser-test",
    "tv-check",
    "tv-clippy",
    "tv-test",
    "local-unity-test"
  ],
  "python_docs_only_skip_steps": [
    "build",
    "clippy",
    "test-core",
    "local-unity-test"
  ],
  "parser_steps": [
    "parser-test"
  ],
  "tv_steps": [
    "tv-check",
    "tv-clippy",
    "tv-test"
  ],
  "python_steps": [
    "python-test",
    "pyre-check"
  ],
  "csharp_steps": [
    "local-unity-test"
  ]
}
